<?xml version="1.0" encoding="UTF-8" standalone="no"?><?xml-stylesheet type="text/xsl" href="https://portal.rosreestr.ru/xsl/EGRP_FIR/Reestr_Extract_Object/03/Common.xsl"?><Extract><eDocument CodeType="112" Scope="EGRP" Version="03"><Sender Appointment="Государственный регистратор" Date_Upload="2016-07-18+03:00" E_Mail="значение отсутствует" FIO="Федеральный информационный ресурс" Kod="00.0.7.3" Name="Федеральный информационный ресурс" Region="99" Telephone="значение отсутствует"/><Recipient Kod="00.0.4.111"/></eDocument><ReestrExtract><DeclarAttribute ExtractCount="1" ExtractDate="18.07.2016" ExtractNumber="90-21662768" ExtractTypeCode="010000" ExtractTypeText="выписка из Единого государственного реестра прав на недвижимое имущество и сделок с ним" ID_KUVI="123456" NoticeCount="0" OfficeDate="18.07.2016" OfficeNumber="90-21662768" RefuseCount="0" Registrator="Федеральный информационный ресурс" RequeryDate="18.07.2016" RequeryNumber="90-21662768"><Representativ>значение отсутствует</Representativ><ReceivAdress>значение отсутствует</ReceivAdress></DeclarAttribute><ExtractObjectRight><HeadContent><ID_REC_KUVI/><Title>ФЕДЕРАЛЬНАЯ СЛУЖБА ГОСУДАРСТВЕННОЙ РЕГИСТРАЦИИ, КАДАСТРА И КАРТОГРАФИИ</Title><DeptName>Федеральный информационный ресурс</DeptName><ExtractTitle>ВЫПИСКА ИЗ ЕДИНОГО ГОСУДАРСТВЕННОГО РЕЕСТРА ПРАВ НА НЕДВИЖИМОЕ ИМУЩЕСТВО И СДЕЛОК С НИМ</ExtractTitle><Content>На основании запроса №90-21662768 от 18.07.2016, поступившего на рассмотрение 18.07.2016 , сообщаем, что в Едином государственном реестре прав на недвижимое имущество и сделок с ним зарегистрировано:</Content></HeadContent><ExtractObject><ObjectRight><ObjectDesc><ID_Object>243324311652</ID_Object><CadastralNumber>52:18:0020112:253</CadastralNumber><ObjectType>002002002000</ObjectType><ObjectTypeText>Помещение</ObjectTypeText><Name>КВАРТИРА</Name><Assignation_Code_Text>ЖИЛОЕ</Assignation_Code_Text><Area><Area>46.7</Area><AreaText>46.7 Квадратный метр</AreaText><Unit>012002001000</Unit></Area><Inv_No/><Floor>5   </Floor><Address><ID_Address>243324311752</ID_Address><Content>Нижегородская область, г.Нижний Новгород, Московский район, ул.Баранова, д.9, кв.90</Content><Region Code="52" Name="Нижегородская область"/><Code_OKATO>22401370000</Code_OKATO><Code_KLADR>52000001000006200</Code_KLADR><City Name="Нижний Новгород,Московский район" Type="г"/><Street Name="Баранова" Type="ул"/><Level1 Name="9" Type=""/><Apartment Name="90" Type=""/></Address></ObjectDesc><Right><Owner><ID_Subject>243324312952</ID_Subject><Person><Code_SP>007003000000</Code_SP><Content>Войтков Игорь Иванович </Content><FIO><Surname>Войтков</Surname><First>Игорь</First><Patronymic>Иванович</Patronymic></FIO><Citizen/></Person></Owner><Owner><ID_Subject>243324313252</ID_Subject><Person><Code_SP>007003000000</Code_SP><Content>Войткова Вера Владимировна </Content><FIO><Surname>Войткова</Surname><First>Вера</First><Patronymic>Владимировна</Patronymic></FIO><Citizen/></Person></Owner><Owner><ID_Subject>243324313652</ID_Subject><Person><Code_SP>007003000000</Code_SP><Content>Смирнова Елена Игоревна </Content><FIO><Surname>Смирнова</Surname><First>Елена</First><Patronymic>Игоревна</Patronymic></FIO><Citizen/></Person></Owner><Owner><ID_Subject>243324314052</ID_Subject><Person><Code_SP>007003000000</Code_SP><Content>Смирнова Дарья Вадимовна </Content><FIO><Surname>Смирнова</Surname><First>Дарья</First><Patronymic>Вадимовна</Patronymic></FIO><Citizen/></Person></Owner><Registration><ID_Record>243324312752</ID_Record><RegNumber>52-01/02-42/2001-56</RegNumber><Type>001003000000</Type><Name>Совместная собственность 52-01/02-42/2001-56 10.05.2001</Name><RegDate>10.05.2001</RegDate><EndDate/></Registration><NoEncumbrance>Не зарегистрировано</NoEncumbrance></Right><NoShareHolding/></ObjectRight><RightAssert/><RightClaim/></ExtractObject><FootContent><Recipient/><ExtractDate>18.07.2016</ExtractDate><Content>В соответствии со статьей 7 Федерального закона от 21 июля 1997 г. № 122-ФЗ «О государственной регистрации прав на недвижимое имущество и сделок с ним» использование сведений, содержащихся в настоящей выписке, способами или в форме, которые наносят ущерб правам и законным интересам правообладателей, влечет ответственность, предусмотренную законодательством Российской Федерации.</Content></FootContent></ExtractObjectRight></ReestrExtract></Extract>